astrotools/__init__.py
astrotools/auger.py
astrotools/container.py
astrotools/coord.py
astrotools/cosmic_rays.py
astrotools/gamale.py
astrotools/healpytools.py
astrotools/nucleitools.py
astrotools/obs.py
astrotools/simulations.py
astrotools/skymap.py
astrotools/statistics.py
astrotools/data/Lunardini_SBG_catalog.dat
astrotools/data/auger_spectrum_2013.txt
astrotools/data/auger_spectrum_2015.txt
astrotools/data/auger_spectrum_2017.txt
astrotools/data/auger_spectrum_2020.txt
astrotools/data/comp/comp-eps-4-tot.dat
astrotools/data/comp/comp-q04-4-tot.dat
astrotools/data/comp/comp-s21-4-tot.dat
astrotools/data/comp/comp_all_2017.dat
astrotools/data/lnA/lnA_EPOS-LHC.txt
astrotools/data/lnA/lnA_QGSJetII-04.txt
astrotools/data/lnA/lnA_Sibyll2.1.txt
astrotools/data/xmax/README
astrotools/data/xmax/acceptance.txt
astrotools/data/xmax/acceptanceNoFOV.txt
astrotools/data/xmax/correlationSysMinus.txt
astrotools/data/xmax/correlationSysPlus.txt
astrotools/data/xmax/example.C
astrotools/data/xmax/resolution.txt
astrotools/data/xmax/resolutionNoFOV.txt
astrotools/data/xmax/xmaxHistograms.txt
astrotools/data/xmax/xmaxMoments.txt
astrotools/data/xmax/xmaxMoments17.txt
astrotools/data/xmax/xmaxMoments19.txt
astrotools/data/xmax/xmaxSystematics.txt
astrotools/simulation/crpropa3__emin_18.5__emax_21.0__IRB_Dominguez11.npz
astrotools/simulation/crpropa3__emin_18.5__emax_21.0__IRB_Gilmore12.npz
astrotools/simulation/crpropa3__emin_18.5__emax_21.0__IRB_Kneiske04.npz
astrotools-1.5.0.dist-info/LICENCE.txt
astrotools-1.5.0.dist-info/METADATA
astrotools-1.5.0.dist-info/WHEEL
astrotools-1.5.0.dist-info/top_level.txt
astrotools-1.5.0.dist-info/RECORD
