Metadata-Version: 2.1
Name: astrotools
Version: 1.5.0
Summary: Python Astro Tools
Home-page: http://astro.pages.rwth-aachen.de/astrotools/
Author: Teresa Bister, Martin Urban, David Walz, Marcus Wirtz
Author-email: bister@physik.rwth-aachen.de, murban@physik.rwth-aachen.de, walz@physik.rwth-aachen.de, mwirtz@physik.rwth-aachen.de
License: MIT
Project-URL: Documentation, http://astro.pages.rwth-aachen.de/astrotools/
Project-URL: Source, https://git.rwth-aachen.de/astro/astrotools
Project-URL: Tutorial, http://astro.pages.rwth-aachen.de/astrotools/tutorial.html
Keywords: astro auger
Platform: UNKNOWN
Classifier: Development Status :: 4 - Beta
Classifier: Intended Audience :: Developers
Classifier: Topic :: Software Development :: Build Tools
Classifier: License :: OSI Approved :: MIT License
Classifier: Programming Language :: Python :: 2
Classifier: Programming Language :: Python :: 3
Requires-Dist: numpy
Requires-Dist: healpy
Requires-Dist: matplotlib
Requires-Dist: scipy
